{"uuid": "315e0e6e-ffe2-4f2e-abee-00f22250aaa2", "tweet_id": "1337981824828649474", "replies": [], "reply_to": null, "avatar": "https://pbs.twimg.com/profile_images/451667745759707136/a1QnbaZ7_normal.jpeg", "user_handle": "Mango_News", "user_name": "Mango News", "content": "US President Donald Trump announced that the vaccine will be free for all Americans and has thanked all the scientists, doctors, and workers for the vaccine.\n\n#USPresident #DonaldTrump #FreeVaccine #Pfizer #PfizerCovidVaccine #PfizerBioNTech #Coronavirus #COVIDVaccine #MangoNews", "date": "", "engagement": "12:45 PM \u00b7 Dec 13, 2020\u00b7TweetDeck", "avatar_extension": "jpeg"}