{"uuid": "7d072c74-c029-4679-bf39-5ab33374621a", "tweet_id": "1338782375602315264", "replies": [], "reply_to": null, "avatar": "https://pbs.twimg.com/profile_images/488226565239492609/nOx4zcpF_normal.png", "user_handle": "NrIsodera", "user_name": "NR", "content": "Each #PfizerBioNTech #COVID19Vaccine vial contains 5 doses - just caught a glimpse of one vial's label on @CNNnewsroom (insufficient time to take a shot: camera shot! ) which apparently need to be premixed, according to the news (canna recall which channel, as I channel surf)!", "date": "5:46 PM \u00b7 Dec 15, 2020\u00b7Twitter for Android", "engagement": "1 Quote Tweet", "avatar_extension": "png"}